uassist/__init__.py
uassist/common.py
uassist/conversions.py
uassist/imgtag.py
uassist/toolbar.py
uassist/uassist.py
uassist-0.0.7.dist-info/LICENSE
uassist-0.0.7.dist-info/METADATA
uassist-0.0.7.dist-info/WHEEL
uassist-0.0.7.dist-info/dependency_links.txt
uassist-0.0.7.dist-info/top_level.txt
uassist-0.0.7.dist-info/RECORD
