Metadata-Version: 2.1
Name: uassist
Version: 0.0.7
Summary: UASsist: Assistant for Unmanned Aircraft System photogrammetry for surveying and mapping applications. 
Home-page: https://github.com/nathanmckinney/uassist
Author: Nathan McKinney
Author-email: mckinney@utk.edu
License: GNU General Public License v3
Keywords: uassist
Platform: UNKNOWN
Classifier: Development Status :: 2 - Pre-Alpha
Classifier: Intended Audience :: Developers
Classifier: License :: OSI Approved :: GNU General Public License v3 (GPLv3)
Classifier: Natural Language :: English
Classifier: Programming Language :: Python :: 3
Classifier: Programming Language :: Python :: 3.5
Classifier: Programming Language :: Python :: 3.6
Classifier: Programming Language :: Python :: 3.7
Classifier: Programming Language :: Python :: 3.8
Requires-Python: >=3.5
Requires-Dist: earthengine-api
Requires-Dist: exifread
Requires-Dist: geojson
Requires-Dist: geopandas
Requires-Dist: ipyleaflet
Requires-Dist: ipyfilechooser
Requires-Dist: pandas
Requires-Dist: pyshp
